django_dockerizer/__init__.py
django_dockerizer/contents.py
django_dockerizer/dockerizer.py
django_dockerizer/utils.py
django_dockerizer-0.3.0.dist-info/LICENSE
django_dockerizer-0.3.0.dist-info/METADATA
django_dockerizer-0.3.0.dist-info/WHEEL
django_dockerizer-0.3.0.dist-info/entry_points.txt
django_dockerizer-0.3.0.dist-info/top_level.txt
django_dockerizer-0.3.0.dist-info/RECORD
