Metadata-Version: 2.1
Name: django-dockerizer
Version: 0.3.0
Summary: Dockerize and make ready to deploy Django projects
Home-page: https://github.com/arifogluisa/django-dockerizer
Author: Isa Arifoglu
Author-email: arifogluisa@gmail.com
License: MIT
Classifier: License :: OSI Approved :: MIT License
Classifier: Programming Language :: Python :: 3.8
Classifier: Operating System :: OS Independent
Requires-Python: >=3.8
License-File: LICENSE
